atomik/__init__.py
atomik/_atomik.py
atomik/_rename_linux.py
atomik/_rename_osx.py
atomik/_version.py
atomik/errors.py
atomik/flags.py
atomik/py.typed
atomik/rename.py
atomik-0.0.3rc1.dist-info/METADATA
atomik-0.0.3rc1.dist-info/WHEEL
atomik-0.0.3rc1.dist-info/licenses/LICENSE
atomik-0.0.3rc1.dist-info/RECORD
