Metadata-Version: 2.3
Name: atomik
Version: 0.0.3rc1
Summary: Atomik provides you a python-friendly way to manage writing new file and folders in an atomic way.
Project-URL: Homepage, https://github.com/halbow/atomik
Project-URL: Bug Tracker, https://github.com/halbow/atomik/issues
Author: halbow
License-File: LICENSE
Classifier: License :: OSI Approved :: MIT License
Classifier: Operating System :: OS Independent
Classifier: Programming Language :: Python :: 3
Classifier: Typing :: Typed
Requires-Python: >=3.8
Provides-Extra: dev
Requires-Dist: mypy; extra == 'dev'
Requires-Dist: pytest; extra == 'dev'
Requires-Dist: pytest-cov; extra == 'dev'
Requires-Dist: ruff; extra == 'dev'
